quarg.py
quarg-0.1.data/scripts/quarg
quarg-0.1.dist-info/DESCRIPTION.rst
quarg-0.1.dist-info/METADATA
quarg-0.1.dist-info/RECORD
quarg-0.1.dist-info/WHEEL
quarg-0.1.dist-info/metadata.json
quarg-0.1.dist-info/top_level.txt
