Metadata-Version: 2.0
Name: quarg
Version: 0.1
Summary: Effortless CLI
Home-page: https://github.com/CydarLtd/quarg
Author: Rob Hague
Author-email: rob.hague@cydar.co.uk
License: MIT
Keywords: command line commandline argument arguments option options argv parsing
Platform: UNKNOWN
Classifier: Development Status :: 3 - Alpha
Classifier: Environment :: Console
Classifier: License :: OSI Approved :: MIT License
Classifier: Operating System :: OS Independent
Classifier: Programming Language :: Python
Classifier: Programming Language :: Python :: 3
Classifier: Programming Language :: Python :: 3.5
Classifier: Programming Language :: Python :: 3.6
Classifier: Programming Language :: Python :: 2.7
